MANIFEST.in
README.rst
setup.py
libzbar/__init__.py
libzbar/ffi_build.py
libzbar/zbar-0.10-noifdefs.h
libzbar_cffi.egg-info/PKG-INFO
libzbar_cffi.egg-info/SOURCES.txt
libzbar_cffi.egg-info/dependency_links.txt
libzbar_cffi.egg-info/pbr.json
libzbar_cffi.egg-info/requires.txt
libzbar_cffi.egg-info/top_level.txt
test/test_libzbar.py