Metadata-Version: 1.1
Name: libzbar-cffi
Version: 0.2.1
Summary: Efficient cffi-based bindings for the zbar QR decoder (Py2, Py3, and PyPy)
Home-page: https://github.com/wolever/libzbar-cffi
Author: David Wolever
Author-email: david@wolever.net
License: UNKNOWN
Platform: UNKNOWN
Classifier: Development Status :: 4 - Beta
Classifier: Programming Language :: Python :: 2
Classifier: Programming Language :: Python :: 3
Classifier: Programming Language :: Python :: Implementation :: PyPy
Classifier: License :: OSI Approved :: BSD License
